taskloop/__init__.py
taskloop/loop.py
taskloop-0.4.1.dist-info/entry_points.txt
taskloop-0.4.1.dist-info/WHEEL
taskloop-0.4.1.dist-info/METADATA
taskloop-0.4.1.dist-info/RECORD
